zynamon/__init__.py
zynamon/cli.py
zynamon/imex.py
zynamon/utils.py
zynamon/xutils.py
zynamon/zeit.py
zynamon-0.1.1.dist-info/licenses/LICENSE
zynamon-0.1.1.dist-info/METADATA
zynamon-0.1.1.dist-info/WHEEL
zynamon-0.1.1.dist-info/entry_points.txt
zynamon-0.1.1.dist-info/top_level.txt
zynamon-0.1.1.dist-info/RECORD
