Metadata-Version: 2.4
Name: zynamon
Version: 0.1.1
Summary: Generalized & powerful time-series class and related functions
Author-email: "Dr. Marcus Zeller" <dsp4444@gmail.com>
License-Expression: GPL-3.0-or-later
Project-URL: Homepage, https://github.com/zynt3c/zynamon
Project-URL: Package, https://pypi.org/project/zynamon/
Keywords: timeseries,analysis,monitoring,prediction,visualisation
Classifier: Programming Language :: Python :: 3
Classifier: Operating System :: Microsoft :: Windows
Requires-Python: >=3.8
License-File: LICENSE
Requires-Dist: h5py~=3.15.1
Requires-Dist: numpy~=2.3.5
Requires-Dist: pandas~=2.3.3
Requires-Dist: pyarrow~=22.0.0
Requires-Dist: scipy~=1.16.3
Requires-Dist: typer~=0.20.0
Dynamic: license-file
